pilotme/__init__.py
pilotbyme-0.0.3.dist-info/METADATA
pilotbyme-0.0.3.dist-info/WHEEL
pilotbyme-0.0.3.dist-info/top_level.txt
pilotbyme-0.0.3.dist-info/RECORD
